flexible_semantic_kernel/__init__.py
flexible_semantic_kernel/kernel.py
flexible_semantic_kernel/kernel_exception.py
flexible_semantic_kernel/sk_pydantic.py
flexible_semantic_kernel/connectors/__init__.py
flexible_semantic_kernel/connectors/telemetry.py
flexible_semantic_kernel/connectors/ai/__init__.py
flexible_semantic_kernel/connectors/ai/ai_exception.py
flexible_semantic_kernel/connectors/ai/ai_request_settings.py
flexible_semantic_kernel/connectors/ai/ai_service_client_base.py
flexible_semantic_kernel/connectors/ai/chat_completion_client_base.py
flexible_semantic_kernel/connectors/ai/text_completion_client_base.py
flexible_semantic_kernel/connectors/ai/embeddings/embedding_generator_base.py
flexible_semantic_kernel/connectors/ai/google_palm/__init__.py
flexible_semantic_kernel/connectors/ai/google_palm/gp_request_settings.py
flexible_semantic_kernel/connectors/ai/google_palm/services/gp_chat_completion.py
flexible_semantic_kernel/connectors/ai/google_palm/services/gp_text_completion.py
flexible_semantic_kernel/connectors/ai/google_palm/services/gp_text_embedding.py
flexible_semantic_kernel/connectors/ai/hugging_face/__init__.py
flexible_semantic_kernel/connectors/ai/hugging_face/hf_request_settings.py
flexible_semantic_kernel/connectors/ai/hugging_face/services/hf_text_completion.py
flexible_semantic_kernel/connectors/ai/hugging_face/services/hf_text_embedding.py
flexible_semantic_kernel/connectors/ai/ollama/__init__.py
flexible_semantic_kernel/connectors/ai/ollama/ollama_request_settings.py
flexible_semantic_kernel/connectors/ai/ollama/utils.py
flexible_semantic_kernel/connectors/ai/ollama/services/ollama_chat_completion.py
flexible_semantic_kernel/connectors/ai/ollama/services/ollama_text_completion.py
flexible_semantic_kernel/connectors/ai/ollama/services/ollama_text_embedding.py
flexible_semantic_kernel/connectors/ai/open_ai/__init__.py
flexible_semantic_kernel/connectors/ai/open_ai/const.py
flexible_semantic_kernel/connectors/ai/open_ai/utils.py
flexible_semantic_kernel-1.0.3.dev0.dist-info/METADATA
flexible_semantic_kernel-1.0.3.dev0.dist-info/WHEEL
flexible_semantic_kernel-1.0.3.dev0.dist-info/top_level.txt
flexible_semantic_kernel-1.0.3.dev0.dist-info/RECORD
