Metadata-Version: 2.1
Name: flexible_semantic_kernel
Version: 1.0.3.dev0
Summary: flexible-semantic-kernel
Author-email: YitongCao <ytea.cao@gmail.com>
Classifier: Programming Language :: Python :: 3
Classifier: License :: OSI Approved :: MIT License
Classifier: Operating System :: OS Independent
Requires-Python: >=3.10
Requires-Dist: aiohttp >=3.8
Requires-Dist: numpy >=1.24.2
Requires-Dist: openai >=1.0
Requires-Dist: aiofiles >=23.1.0
Requires-Dist: python-dotenv ==1.0.0
Requires-Dist: regex >=2023.6.3
Requires-Dist: openapi-core >=0.18.0
Requires-Dist: prance >=23.6.21.0
Requires-Dist: pydantic >2
Requires-Dist: motor >=3.3.1
Requires-Dist: pre-commit ==3.5.0
Requires-Dist: black >=23.12.0
Requires-Dist: ruff ==0.2.2
Requires-Dist: ipykernel >=6.21.1
Requires-Dist: pytest ==7.4.3
Requires-Dist: pytest-asyncio ==0.23.2
Requires-Dist: snoop ==0.4.3
Requires-Dist: pytest-cov ==4.1.0
Requires-Dist: google-generativeai <0.3,>=0.1
Requires-Dist: grpcio-status >=1.53.0
Requires-Dist: transformers >=4.28.1
Requires-Dist: sentence-transformers >=2.2.2
Requires-Dist: torch ==2.0.0
Requires-Dist: qdrant-client >=1.3.2
Requires-Dist: chromadb ==0.4.24
Requires-Dist: pymilvus ==2.3.7
Requires-Dist: milvus ==2.3.8
Requires-Dist: weaviate-client >=3.18.0
Requires-Dist: pinecone-client >=2.2.2
Requires-Dist: psycopg-pool >=3.1.7
Requires-Dist: psycopg >=3.1.9
Requires-Dist: psycopg-binary >=3.1.9
Requires-Dist: redis >=4.6.0
Requires-Dist: usearch ==1.1.1
Requires-Dist: pyarrow <15.0.0,>=12.0.1
